super_ivim_dc/__init__.py
super_ivim_dc/directories.py
super_ivim_dc/exp1_numerical_simulations.py
super_ivim_dc/exp2_healthy_vol_study.py
super_ivim_dc/exp3_fetal_data.py
super_ivim_dc/infer.py
super_ivim_dc/main.py
super_ivim_dc/train.py
super_ivim_dc/IVIMNET/__init__.py
super_ivim_dc/IVIMNET/deep.py
super_ivim_dc/IVIMNET/fitting_algorithms.py
super_ivim_dc/IVIMNET/inference.py
super_ivim_dc/IVIMNET/simulations.py
super_ivim_dc/source/Classsic_ivim_fit.py
super_ivim_dc/source/__init__.py
super_ivim_dc/source/fetal_pre_processing.py
super_ivim_dc/source/hunan_pre_processing.py
super_ivim_dc/source/hyperparams.py
super_ivim_dc/source/plot.py
super_ivim_dc/source/train_model.py
super_ivim_dc/source/utiles.py
super_ivim_dc-1.2.0.dist-info/licenses/LICENSE
super_ivim_dc-1.2.0.dist-info/METADATA
super_ivim_dc-1.2.0.dist-info/WHEEL
super_ivim_dc-1.2.0.dist-info/entry_points.txt
super_ivim_dc-1.2.0.dist-info/top_level.txt
super_ivim_dc-1.2.0.dist-info/RECORD
