Metadata-Version: 2.4
Name: super-ivim-dc
Version: 1.2.0
License-Expression: GPL-3.0-or-later
License-File: LICENSE
Requires-Dist: numpy
Requires-Dist: scipy
Requires-Dist: matplotlib
Requires-Dist: pandas
Requires-Dist: SimpleITK
Requires-Dist: torch
Requires-Dist: tqdm
Requires-Dist: joblib
Provides-Extra: bobyqa
Requires-Dist: nlopt; sys_platform == "linux" and extra == "bobyqa"
Dynamic: license-file
